guildmaster/__init__.py
guildmaster/cli.py
guildmaster/client/_init_.py
guildmaster/client/discord_client.py
guildmaster/config/__init__.py
guildmaster/config/logger.py
guildmaster/tasks/_init_.py
guildmaster/tasks/role_manager.py
guildmaster_cli-1.1.3.dist-info/licenses/LICENSE
guildmaster_cli-1.1.3.dist-info/METADATA
guildmaster_cli-1.1.3.dist-info/WHEEL
guildmaster_cli-1.1.3.dist-info/entry_points.txt
guildmaster_cli-1.1.3.dist-info/top_level.txt
guildmaster_cli-1.1.3.dist-info/zip-safe
guildmaster_cli-1.1.3.dist-info/RECORD
